{"focus":false,"widget/default-greeting":null,"widget/U9khwFOeJzrG":null,"widget/EjzWn_Nq6ttt":{"id":"EjzWn_Nq6ttt","key":"widget/search","order":2,"display":{"position":"middleCentre"}},"widget/a2jw0v6xcyqe":null,"data/default-time":{"mode":"digital","hour12":false,"showDate":false,"showMinutes":true,"showSeconds":false,"showDayPeriod":true,"timeZone":null},"background":{"id":"8jyQxQNvUE3k","key":"background/image","display":{"blur":6,"luminosity":-0.1}},"widget/D9wxmhmZoyL7":null,"widget/LAhD7RT6f3kt":{"id":"LAhD7RT6f3kt","key":"widget/weather","order":3,"display":{"position":"bottomCentre"}},"data/LAhD7RT6f3kt":{"showDetails":false,"units":"si","latitude":28.652,"longitude":77.2315,"name":"Terabithia"},"widget/default-time":{"id":"default-time","key":"widget/time","order":0,"display":{"position":"middleCentre"}},"locale":"en","timeZone":null,"version":3}